trafaret_schema/__init__.py
trafaret_schema/decimal.py
trafaret_schema/format.py
trafaret_schema/utils.py
trafaret_schema-0.2.1.dist-info/DESCRIPTION.rst
trafaret_schema-0.2.1.dist-info/METADATA
trafaret_schema-0.2.1.dist-info/RECORD
trafaret_schema-0.2.1.dist-info/WHEEL
trafaret_schema-0.2.1.dist-info/metadata.json
trafaret_schema-0.2.1.dist-info/top_level.txt
