Metadata-Version: 2.0
Name: trafaret-schema
Version: 0.2.1
Summary: Validation and parsing library
Home-page: https://github.com/Deepwalker/trafaret_schema/
Author: Deepwalker
Author-email: krivushinme@gmail.com
License: BSD
Keywords: validation form forms data schema
Platform: UNKNOWN
Classifier: Intended Audience :: Developers
Classifier: License :: OSI Approved :: BSD License
Classifier: Operating System :: OS Independent
Classifier: Programming Language :: Python
Classifier: Programming Language :: Python :: 3
Requires-Dist: trafaret
